ssakssree/__init__.py
ssakssree/recommender.py
ssakssree-0.1.0.dist-info/LICENSE
ssakssree-0.1.0.dist-info/METADATA
ssakssree-0.1.0.dist-info/WHEEL
ssakssree-0.1.0.dist-info/top_level.txt
ssakssree-0.1.0.dist-info/RECORD
