Metadata-Version: 2.1
Name: ssakssree
Version: 0.1.0
Summary: A collection of statistics-based business analysis libraries by Danda Company, a professional analytics firm
Home-page: https://github.com/dandacompany/ssakssree
Author: Danda Company
Author-email: datapod.k@gmail.com
Classifier: Programming Language :: Python :: 3
Classifier: License :: OSI Approved :: MIT License
Classifier: Operating System :: OS Independent
Requires-Python: >=3.6
License-File: LICENSE
Requires-Dist: pandas>=1.0.0
Requires-Dist: statsmodels>=0.12.0
